openapi/_hooks/registration.py
squadcast_sdk/__init__.py
squadcast_sdk/_version.py
squadcast_sdk/additionalresponders.py
squadcast_sdk/analytics.py
squadcast_sdk/apitoken.py
squadcast_sdk/apitokens.py
squadcast_sdk/auditlogs.py
squadcast_sdk/autopausetransientalerts.py
squadcast_sdk/basesdk.py
squadcast_sdk/communicationcard.py
squadcast_sdk/communicationcards.py
squadcast_sdk/componentgroups.py
squadcast_sdk/components.py
squadcast_sdk/dedupkey.py
squadcast_sdk/dedupkeys.py
squadcast_sdk/deduplicationrules.py
squadcast_sdk/dependencies.py
squadcast_sdk/escalationpolicies_sdk.py
squadcast_sdk/events.py
squadcast_sdk/exports.py
squadcast_sdk/exportschedule.py
squadcast_sdk/extensions.py
squadcast_sdk/extensions_webhooks.py
squadcast_sdk/falsepositive.py
squadcast_sdk/globaleventrules.py
squadcast_sdk/globaleventrules_rulesets.py
squadcast_sdk/globaloncallreminderrules_sdk.py
squadcast_sdk/httpclient.py
squadcast_sdk/incidentactions.py
squadcast_sdk/incidents.py
squadcast_sdk/incidents_actions.py
squadcast_sdk/incidents_additionalresponders.py
squadcast_sdk/incidents_communicationcards.py
squadcast_sdk/incidents_export.py
squadcast_sdk/incidents_postmortems.py
squadcast_sdk/incidents_snoozenotifications.py
squadcast_sdk/incidents_tags.py
squadcast_sdk/issues.py
squadcast_sdk/jira.py
squadcast_sdk/logs.py
squadcast_sdk/maintenance.py
squadcast_sdk/maintenancemode.py
squadcast_sdk/maintenances.py
squadcast_sdk/msteams_1.py
squadcast_sdk/msteams_2.py
squadcast_sdk/notes.py
squadcast_sdk/overlay.py
squadcast_sdk/overlay_customcontenttemplates.py
squadcast_sdk/overlays.py
squadcast_sdk/overlays_customcontenttemplates.py
squadcast_sdk/overrides.py
squadcast_sdk/postmortems_sdk.py
squadcast_sdk/py.typed
squadcast_sdk/roles.py
squadcast_sdk/rotations.py
squadcast_sdk/routingrules.py
squadcast_sdk/rules.py
squadcast_sdk/rulesets.py
squadcast_sdk/rulesets_rules.py
squadcast_sdk/runbooks_sdk.py
squadcast_sdk/schedules_export.py
squadcast_sdk/schedules_overrides.py
squadcast_sdk-0.3.3.dist-info/METADATA
squadcast_sdk-0.3.3.dist-info/WHEEL
squadcast_sdk-0.3.3.dist-info/top_level.txt
squadcast_sdk-0.3.3.dist-info/RECORD
